{"_id":{"$oid":"5b9a9eb1d827151d144f8db4"},"uid":{"$oid":"5b9a9e64d827151d144f8daf"},"orderNumber":"1536859823603","totalPrice":20,"city":"jerusalem","street":"stam","deliveryDate":"2018-09-29","creditCard":0,"purchaseDate":{"$date":"2018-09-13T17:30:25.700Z"},"__v":0}
{"_id":{"$oid":"5b9ac711777da750641df395"},"uid":{"$oid":"5b9a9e64d827151d144f8daf"},"orderNumber":"1536870159161","totalPrice":4,"city":"jerusalem","street":"stam","deliveryDate":"2018-09-28","creditCard":0,"purchaseDate":{"$date":"2018-09-13T20:22:41.291Z"},"__v":0}
{"_id":{"$oid":"5b9ac73cd16fe126a886445b"},"uid":{"$oid":"5b9a9e64d827151d144f8daf"},"orderNumber":"1536870202652","totalPrice":20,"city":"jerusalem","street":"stam","deliveryDate":"2018-09-21","creditCard":0,"purchaseDate":{"$date":"2018-09-13T20:23:24.758Z"},"__v":0}
{"_id":{"$oid":"5b9ac7719ff9ee04142f6f7e"},"uid":{"$oid":"5b9a9e64d827151d144f8daf"},"orderNumber":"1536870255439","totalPrice":40,"city":"jerusalem","street":"stam","deliveryDate":"2018-09-27","creditCard":0,"purchaseDate":{"$date":"2018-09-13T20:24:17.543Z"},"__v":0}
{"_id":{"$oid":"5b9ac78cd41bf352dcb9ea9d"},"uid":{"$oid":"5b9a9e64d827151d144f8daf"},"orderNumber":"1536870282565","totalPrice":20,"city":"jerusalem","street":"stam","deliveryDate":"2018-09-29","creditCard":0,"purchaseDate":{"$date":"2018-09-13T20:24:44.582Z"},"__v":0}
{"_id":{"$oid":"5b9ac7b5809b334f246e4332"},"uid":{"$oid":"5b9a9e64d827151d144f8daf"},"orderNumber":"1536870322979","totalPrice":20,"city":"jerusalem","street":"stam","deliveryDate":"2018-09-28","creditCard":0,"purchaseDate":{"$date":"2018-09-13T20:25:25.096Z"},"__v":0}
{"_id":{"$oid":"5b9ac8327cd83d51cc620e3a"},"uid":{"$oid":"5b9a9e64d827151d144f8daf"},"orderNumber":"1536870448377","totalPrice":20,"city":"jerusalem","street":"stam","deliveryDate":"2018-09-28","creditCard":0,"purchaseDate":{"$date":"2018-09-13T20:27:30.483Z"},"__v":0}
{"_id":{"$oid":"5b9ac8467cd83d51cc620e3d"},"uid":{"$oid":"5b9a9e64d827151d144f8daf"},"orderNumber":"1536870468658","totalPrice":40,"city":"jerusalem","street":"stam","deliveryDate":"2018-09-14","creditCard":0,"purchaseDate":{"$date":"2018-09-13T20:27:50.749Z"},"__v":0}
{"_id":{"$oid":"5b9acae27cd83d51cc620e41"},"uid":{"$oid":"5b9a9e64d827151d144f8daf"},"orderNumber":"1536871136440","totalPrice":20,"city":"jerusalem","street":"stam","deliveryDate":"2018-09-27","creditCard":0,"purchaseDate":{"$date":"2018-09-13T20:38:58.521Z"},"__v":0}
{"_id":{"$oid":"5b9acc617cd83d51cc620e4a"},"uid":{"$oid":"5b9a9e64d827151d144f8daf"},"orderNumber":"1536871519708","totalPrice":20,"city":"jerusalem","street":"stam","deliveryDate":"2018-09-29","creditCard":0,"purchaseDate":{"$date":"2018-09-13T20:45:21.800Z"},"__v":0}
